localdrop/__init__.py
localdrop/__main__.py
localdrop/cilent.py
localdrop/sender.py
localdrop-0.2.1.dist-info/licenses/LICENSE
localdrop-0.2.1.dist-info/METADATA
localdrop-0.2.1.dist-info/WHEEL
localdrop-0.2.1.dist-info/top_level.txt
localdrop-0.2.1.dist-info/RECORD
