Metadata-Version: 2.4
Name: localdrop
Version: 0.2.1
Summary: Local file sharing tool
Author-email: yasir-dev1 <yasireposta3@gmail.com>
License: MIT
License-File: LICENSE
Requires-Dist: click
Dynamic: license-file
